iconcommons/__init__.py
iconcommons/icon_config/__init__.py
iconcommons/icon_config/icon_config.py
iconcommons/logger/__init__.py
iconcommons/logger/logger.py
iconcommons/logger/_logger/__init__.py
iconcommons/logger/_logger/icon_logger_util.py
iconcommons/logger/_logger/icon_period_and_bytes_file_handler.py
iconcommons/logger/_logger/icon_rotating_file_handler.py
iconcommons/logger/_logger/icon_time_rotating_file_handler.py
iconcommons/logger/_logger/utils.py
iconcommons-1.1.3.dist-info/METADATA
iconcommons-1.1.3.dist-info/WHEEL
iconcommons-1.1.3.dist-info/top_level.txt
iconcommons-1.1.3.dist-info/RECORD
