Metadata-Version: 2.1
Name: iconcommons
Version: 1.1.3
Summary: ICON Commmons package for Python
Home-page: https://github.com/icon-project/icon-commons
Author: ICON Foundation
Author-email: foo@icon.foundation
License: Apache License 2.0
Platform: UNKNOWN
Classifier: Development Status :: 5 - Production/Stable
Classifier: Intended Audience :: Developers
Classifier: Intended Audience :: System Administrators
Classifier: Natural Language :: English
Classifier: License :: OSI Approved :: Apache Software License
Classifier: Programming Language :: Python
Classifier: Programming Language :: Python :: 3.6
Classifier: Programming Language :: Python :: 3.7
